ai_skill_manager/__init__.py
ai_skill_manager/cli.py
ai_skill_manager/dependency_manager.py
ai_skill_manager/git_handler.py
ai_skill_manager/git_utils.py
ai_skill_manager/manager.py
ai_skill_manager/skill_types.py
ai_skill_manager-1.0.2.dist-info/licenses/LICENSE
ai_skill_manager-1.0.2.dist-info/METADATA
ai_skill_manager-1.0.2.dist-info/WHEEL
ai_skill_manager-1.0.2.dist-info/entry_points.txt
ai_skill_manager-1.0.2.dist-info/top_level.txt
ai_skill_manager-1.0.2.dist-info/RECORD
