Metadata-Version: 2.4
Name: ai-skill-manager
Version: 1.0.2
Summary: A lightweight utility to download and manage skills for different AI coding assistants
Author-email: AI Skill Manager <contact@example.com>
Project-URL: Homepage, https://github.com/binzhango/agent-skills-util
Project-URL: Repository, https://github.com/binzhango/agent-skills-util
Project-URL: Issues, https://github.com/binzhango/agent-skills-util/issues
Classifier: Development Status :: 5 - Production/Stable
Classifier: Intended Audience :: Developers
Classifier: Operating System :: OS Independent
Classifier: Programming Language :: Python :: 3
Classifier: Programming Language :: Python :: 3.11
Classifier: Programming Language :: Python :: 3.12
Classifier: Topic :: Software Development :: Libraries :: Python Modules
Classifier: Topic :: Software Development :: Code Generators
Classifier: Topic :: Utilities
Requires-Python: >=3.11
License-File: LICENSE
Requires-Dist: requests>=2.25.0
Requires-Dist: click>=8.0.0
Dynamic: license-file
